<?xml version="1.0" standalone="yes"?>
<Spawns>
  <Points>
    <Name>Test</Name>
    <UniqueId>ccf1787d-a526-4376-9b91-29b523a20529</UniqueId>
    <Map>Felucca</Map>
    <X>5699</X>
    <Y>391</Y>
    <Width>0</Width>
    <Height>0</Height>
    <CentreX>0</CentreX>
    <CentreY>0</CentreY>
    <CentreZ>0</CentreZ>
    <Range>5</Range>
    <MaxCount>100</MaxCount>
    <MinDelay>0</MinDelay>
    <MaxDelay>0</MaxDelay>
    <DelayInSec>True</DelayInSec>
    <Duration>0</Duration>
    <ProximityRange>-1</ProximityRange>
    <ProximityTriggerSound>0</ProximityTriggerSound>
    <TriggerProbability>1</TriggerProbability>
    <InContainer>False</InContainer>
    <ContainerX>0</ContainerX>
    <ContainerY>0</ContainerY>
    <ContainerZ>0</ContainerZ>
    <MinRefractory>0</MinRefractory>
    <MaxRefractory>0</MaxRefractory>
    <TODStart>0</TODStart>
    <TODEnd>0</TODEnd>
    <TODMode>0</TODMode>
    <ExternalTriggering>False</ExternalTriggering>
    <SequentialSpawning>0</SequentialSpawning>
    <RegionName />
    <Team>0</Team>
    <Amount>1</Amount>
    <IsGroup>False</IsGroup>
    <IsRunning>False</IsRunning>
    <IsHomeRangeRelative>True</IsHomeRangeRelative>
    <Objects2>EFFECT,14000,25,{GETONTHIS,x},{GETONTHIS,y},{GETONTHIS,z},2:MX=1:SP=1:RT=0:TO=0:CA=0:KL=0:SB=1
		:OBJ=SETONNEARBY,2,*,basecreature/huemod/1152/frozen/true:MX=1:SP=1:RT=0:TO=0:CA=0:KL=0:SB=1
		:OBJ=WAITUNTIL,0.2:MX=1:SP=1:RT=0:TO=0:CA=0:KL=0:SB=2
		:OBJ=SETONNEARBY,2,*,basecreature/huemod/-1/frozen/false:MX=1:SP=1:RT=0:TO=0:CA=0:KL=0:SB=3
		:OBJ=SETONTHIS/DELETE:MX=1:SP=1:RT=0:TO=0:CA=0:KL=0:SB=4
	</Objects2>
  </Points>
</Spawns>